{
  "C:\\Users\\Christopeer\\Downloads\\TallerIntegrador\\videos\\Traffic IP Camera video.mp4": {
    "main_direction": "up",
    "secondary_direction": null,
    "custom_directions": [
      {
        "canvas_coords": [
          [
            388,
            358
          ],
          [
            514,
            128
          ]
        ],
        "frame_coords": [
          [
            1125,
            952
          ],
          [
            1490,
            340
          ]
        ]
      }
    ]
  },
  "C:\\Users\\Christopeer\\Downloads\\TallerIntegrador\\videos\\YF_DzoTDO-0.mp4": {
    "main_direction": "right",
    "secondary_direction": null,
    "custom_directions": [
      {
        "canvas_coords": [
          [
            186,
            91
          ],
          [
            559,
            326
          ]
        ],
        "frame_coords": [
          [
            719,
            322
          ],
          [
            2161,
            1156
          ]
        ]
      }
    ]
  },
  "C:\\Users\\Christopeer\\Downloads\\TallerIntegrador\\videos\\1080P 2.0Megapixel IP camera video on road.mp4": {
    "main_direction": "up",
    "secondary_direction": "down",
    "custom_directions": [
      {
        "canvas_coords": [
          [
            294,
            358
          ],
          [
            298,
            182
          ]
        ],
        "frame_coords": [
          [
            852,
            952
          ],
          [
            864,
            484
          ]
        ]
      },
      {
        "canvas_coords": [
          [
            371,
            180
          ],
          [
            426,
            379
          ]
        ],
        "frame_coords": [
          [
            1076,
            478
          ],
          [
            1235,
            1008
          ]
        ]
      }
    ]
  },
  "C:\\Users\\Christopeer\\Downloads\\TallerIntegrador\\videos\\W_A4xFDNjnU.mp4": {
    "main_direction": "down",
    "secondary_direction": "up",
    "custom_directions": [
      {
        "canvas_coords": [
          [
            381,
            121
          ],
          [
            430,
            301
          ]
        ],
        "frame_coords": [
          [
            736,
            214
          ],
          [
            831,
            533
          ]
        ]
      },
      {
        "canvas_coords": [
          [
            132,
            297
          ],
          [
            225,
            123
          ]
        ],
        "frame_coords": [
          [
            255,
            526
          ],
          [
            435,
            218
          ]
        ]
      }
    ]
  }
}